saur_client/__init__.py
saur_client/__init__.pyi
saur_client/_version.py
saur_client/_version.pyi
saur_client/saur_client.py
saur_client/saur_client.pyi
saur_client-0.3.2.dist-info/LICENSE
saur_client-0.3.2.dist-info/METADATA
saur_client-0.3.2.dist-info/WHEEL
saur_client-0.3.2.dist-info/top_level.txt
saur_client-0.3.2.dist-info/RECORD
