Metadata-Version: 2.2
Name: saur_client
Version: 0.3.2
Summary: Client Python pour interagir avec l'API SAUR
Author-email: Cekage Dave <github@cekage.net>
License: MIT License
Project-URL: Homepage, https://github.com/cekage/Saur_fr_client
Project-URL: Bug Tracker, http://github.com/cekage/Saur_fr_client/issues
Classifier: Programming Language :: Python :: 3
Classifier: License :: OSI Approved :: MIT License
Classifier: Operating System :: OS Independent
Requires-Python: >=3.12
License-File: LICENSE
Requires-Dist: aiohttp==3.11.11
Requires-Dist: attrs==24.2.0
Requires-Dist: propcache==0.2.1
